MANIFEST.in
setup.py
r3/__init__.py
r3/version.py
r3.egg-info/PKG-INFO
r3.egg-info/SOURCES.txt
r3.egg-info/dependency_links.txt
r3.egg-info/entry_points.txt
r3.egg-info/requires.txt
r3.egg-info/top_level.txt
r3/app/__init__.py
r3/app/app.py
r3/app/config.py
r3/app/keys.py
r3/app/server.py
r3/app/utils.py
r3/app/handlers/__init__.py
r3/app/handlers/healthcheck.py
r3/app/handlers/index.py
r3/app/handlers/stream.py
r3/app/templates/index.html
r3/web/__init__.py
r3/web/app.py
r3/web/config.py
r3/web/extensions.py
r3/web/server.py
r3/web/static/css/bootstrap.min.css
r3/web/static/css/progress.css
r3/web/static/css/reset.css
r3/web/static/css/style.css
r3/web/static/img/logo.png
r3/web/static/js/bootstrap.min.js
r3/web/static/js/jquery-1.7.2.min.js
r3/web/static/js/progress.js
r3/web/static/js/tabs.js
r3/web/templates/failed.html
r3/web/templates/index.html
r3/web/templates/job-types.html
r3/web/templates/mappers.html
r3/web/templates/master.html
r3/web/templates/show_key.html
r3/web/templates/stats.html
r3/worker/__init__.py
r3/worker/mapper.py