Metadata-Version: 1.1
Name: r3
Version: 0.2.0
Summary: r3 is a map-reduce engine written in python
Home-page: http://heynemann.github.com/r3/
Author: Bernardo Heynemann
Author-email: heynemann@gmail.com
License: MIT
Keywords: map reduce
Platform: UNKNOWN
Classifier: Development Status :: 3 - Alpha
Classifier: Intended Audience :: Developers
Classifier: License :: OSI Approved :: MIT License
Classifier: Natural Language :: English
Classifier: Operating System :: MacOS
Classifier: Operating System :: POSIX :: Linux
Classifier: Programming Language :: Python :: 2.6
Classifier: Programming Language :: Python :: 2.7
